{
  "test_loss_values": [
    2.1812265662232573,
    0.7782548069953918
  ],
  "log_exp_r_n_values": [
    3662586.517569928,
    -Infinity
  ],
  "log_exp_r_n_acc_values": [
    -Infinity,
    -Infinity
  ],
  "model_data_levels": [
    19940,
    59940
  ],
  "loss_landscape_data_param": 19940,
  "train_loss_values": [
    0.0006293234182521701,
    0.15127280354499817
  ],
  "num_params": 1707274,
  "dataset_type": "data",
  "top_r_vals": [
    [
      8.544493227731865,
      8.539284894398532,
      8.53892619375574,
      8.537456318232834,
      8.536973268033876,
      8.536267823436384,
      8.535211649321498,
      8.53510643046628,
      8.534548451688604,
      8.534421710794819,
      8.533824673502705,
      8.533531336088155,
      8.533485103560862,
      8.533401406744211,
      8.533336840628508,
      8.533273071625345,
      8.53305785123967,
      8.53290400851954,
      8.532711904397512,
      8.53261067110499,
      8.531754572237528,
      8.531670875420877,
      8.531538554739313,
      8.531293841189676,
      8.531176665646363,
      8.531076229466382,
      8.530821153453731,
      8.53057803412917,
      8.530424988521581,
      8.530333320579533,
      8.530055925415775,
      8.529649398020611,
      8.529641426895216,
      8.529493961075401,
      8.529364031731458,
      8.529245261963066,
      8.529180695847364,
      8.52899735996327,
      8.52849836751352,
      8.527954736761556,
      8.527877416845222,
      8.527571325630039,
      8.527123348382819,
      8.526655443322111,
      8.526428266248343,
      8.52581528670544,
      8.525756300377514,
      8.524895418834813,
      8.524692155137233,
      8.523091553157842
    ],
    [
      0.0,
      0.0,
      0.0,
      0.0,
      0.0,
      0.0,
      0.0,
      0.0,
      0.0,
      0.0,
      0.0,
      0.0,
      0.0,
      0.0,
      0.0,
      0.0,
      0.0,
      0.0,
      0.0,
      0.0,
      0.0,
      0.0,
      0.0,
      0.0,
      0.0,
      0.0,
      0.0,
      0.0,
      0.0,
      0.0,
      0.0,
      0.0,
      0.0,
      0.0,
      0.0,
      0.0,
      0.0,
      0.0,
      0.0,
      0.0,
      0.0,
      0.0,
      0.0,
      0.0,
      0.0,
      0.0,
      0.0,
      0.0,
      0.0,
      0.0
    ]
  ],
  "top_r_val_seeds": [
    [
      440,
      444,
      260,
      251,
      41,
      138,
      208,
      191,
      495,
      371,
      309,
      155,
      36,
      414,
      343,
      290,
      315,
      329,
      169,
      106,
      164,
      497,
      219,
      229,
      489,
      3,
      286,
      346,
      20,
      39,
      75,
      474,
      304,
      326,
      314,
      258,
      117,
      118,
      499,
      331,
      187,
      308,
      115,
      368,
      370,
      265,
      287,
      420,
      479,
      69
    ],
    [
      1,
      2,
      3,
      4,
      5,
      6,
      7,
      8,
      9,
      10,
      11,
      12,
      13,
      14,
      15,
      16,
      17,
      18,
      19,
      20,
      21,
      22,
      23,
      24,
      25,
      26,
      27,
      28,
      29,
      30,
      31,
      32,
      33,
      34,
      35,
      36,
      37,
      38,
      39,
      40,
      41,
      42,
      43,
      44,
      45,
      46,
      47,
      48,
      49,
      50
    ]
  ],
  "loss_predicts_minimas": true,
  "loss_ordering_violations": 1,
  "test_loss_ranks": [
    1,
    2
  ],
  "log_exp_r_n_ranks": [
    1,
    2
  ],
  "data_level_ranks": [
    2,
    1
  ],
  "accuracy_predicts_minimas": true,
  "accuracy_ordering_violations": 1,
  "log_exp_r_n_acc_ranks": [
    1,
    2
  ]
}